pytket/extensions/quest/__init__.py
pytket/extensions/quest/_metadata.py
pytket/extensions/quest/py.typed
pytket/extensions/quest/quest_convert.py
pytket/extensions/quest/backends/__init__.py
pytket/extensions/quest/backends/quest_backend.py
pytket_quest-0.1.0.dist-info/LICENSE
pytket_quest-0.1.0.dist-info/METADATA
pytket_quest-0.1.0.dist-info/WHEEL
pytket_quest-0.1.0.dist-info/top_level.txt
pytket_quest-0.1.0.dist-info/RECORD
