Metadata-Version: 2.1
Name: pytket-quest
Version: 0.1.0
Summary: Extension for pytket, providing access to the QuEST Simulator
Author: TKET development team
Author-email: tket-support@quantinuum.com
License: Apache 2
Project-URL: Documentation, https://tket.quantinuum.com/extensions/pytket-quest/index.html
Project-URL: Source, https://github.com/CQCL/pytket-quest
Project-URL: Tracker, https://github.com/CQCL/pytket-quest/issues
Classifier: Environment :: Console
Classifier: Programming Language :: Python :: 3.10
Classifier: Programming Language :: Python :: 3.11
Classifier: Programming Language :: Python :: 3.12
Classifier: License :: OSI Approved :: Apache Software License
Classifier: Operating System :: MacOS :: MacOS X
Classifier: Operating System :: POSIX :: Linux
Classifier: Operating System :: Microsoft :: Windows
Classifier: Intended Audience :: Developers
Classifier: Intended Audience :: Science/Research
Classifier: Topic :: Scientific/Engineering
Requires-Python: >=3.10
License-File: LICENSE
Requires-Dist: pytket ~=1.34.0
Requires-Dist: pyquest ~=0.0.1
Requires-Dist: numpy <2.0.0,>=1.20
